odoo/addons/project_stock_request/README.rst
odoo/addons/project_stock_request/__init__.py
odoo/addons/project_stock_request/__manifest__.py
odoo/addons/project_stock_request/i18n/es.po
odoo/addons/project_stock_request/i18n/es_AR.po
odoo/addons/project_stock_request/i18n/hr.po
odoo/addons/project_stock_request/i18n/it.po
odoo/addons/project_stock_request/i18n/project_stock_request.pot
odoo/addons/project_stock_request/i18n/pt_BR.po
odoo/addons/project_stock_request/models/__init__.py
odoo/addons/project_stock_request/models/project.py
odoo/addons/project_stock_request/models/project_task.py
odoo/addons/project_stock_request/models/stock_request_order.py
odoo/addons/project_stock_request/readme/CONTRIBUTORS.rst
odoo/addons/project_stock_request/readme/CREDITS.rst
odoo/addons/project_stock_request/readme/DESCRIPTION.rst
odoo/addons/project_stock_request/readme/USAGE.rst
odoo/addons/project_stock_request/security/ir.model.access.csv
odoo/addons/project_stock_request/static/description/icon.png
odoo/addons/project_stock_request/static/description/index.html
odoo/addons/project_stock_request/views/project_task_views.xml
odoo/addons/project_stock_request/views/project_views.xml
odoo/addons/project_stock_request/views/stock_request_order_views.xml
odoo14_addon_project_stock_request-14.0.1.0.1.dev17.dist-info/METADATA
odoo14_addon_project_stock_request-14.0.1.0.1.dev17.dist-info/WHEEL
odoo14_addon_project_stock_request-14.0.1.0.1.dev17.dist-info/top_level.txt
odoo14_addon_project_stock_request-14.0.1.0.1.dev17.dist-info/RECORD
